fleet/__init__.py
fleet/manager.py
fleet/worker.py
fleet/config/__init__.py
fleet/config/config.py
fleet/manager_utils/__init__.py
fleet/manager_utils/assign_jobs.py
fleet/utils/__init__.py
fleet/utils/file_utils.py
fleet/utils/host_utils.py
fleet/utils/time_tracker.py
open_fleet-0.0.7.dist-info/LICENSE
open_fleet-0.0.7.dist-info/METADATA
open_fleet-0.0.7.dist-info/WHEEL
open_fleet-0.0.7.dist-info/top_level.txt
open_fleet-0.0.7.dist-info/RECORD
